sling_linux_amd64/__init__.py
sling_linux_amd64/bin/LICENSE
sling_linux_amd64/bin/README.md
sling_linux_amd64/bin/VERSION
sling_linux_amd64/bin/sling-linux-amd64
sling_linux_amd64-1.4.11.dist-info/METADATA
sling_linux_amd64-1.4.11.dist-info/WHEEL
sling_linux_amd64-1.4.11.dist-info/top_level.txt
sling_linux_amd64-1.4.11.dist-info/RECORD
