Metadata-Version: 2.4
Name: sling-linux-amd64
Version: 1.4.11
Summary: Sling Binary for Linux (AMD64)
Home-page: https://github.com/slingdata-io/sling-python
Download-URL: https://github.com/slingdata-io/sling-python/archive/master.zip
Author: Fritz Larco
Author-email: fritz@slingdata.io
Keywords: sling,etl,elt,extract,load
Classifier: Programming Language :: Python :: 3
Classifier: Intended Audience :: Developers
Classifier: Intended Audience :: Education
Classifier: Intended Audience :: Science/Research
Classifier: Operating System :: MacOS
Classifier: Operating System :: Unix
Classifier: Topic :: Utilities
Dynamic: author
Dynamic: author-email
Dynamic: classifier
Dynamic: description
Dynamic: description-content-type
Dynamic: download-url
Dynamic: home-page
Dynamic: keywords
Dynamic: summary
